<?xml version="1.0" encoding="utf-8" ?><dwsync><file name="1.png" server="69.36.11.79" local="3328821220" remote="24849972320" /><file name="10.png" server="69.36.11.79" local="3328821220" remote="29144939616" /><file name="11.png" server="69.36.11.79" local="3328821220" remote="29144939616" /><file name="12.png" server="69.36.11.79" local="3328821220" remote="29144939616" /><file name="13.png" server="69.36.11.79" local="3328821220" remote="29144939616" /><file name="14.png" server="69.36.11.79" local="3328821220" remote="29144939616" /><file name="15.png" server="69.36.11.79" local="3328821220" remote="29144939616" /><file name="16.png" server="69.36.11.79" local="3328821220" remote="29144939616" /><file name="2.png" server="69.36.11.79" local="3328821220" remote="24849972320" /><file name="3.png" server="69.36.11.79" local="3328821220" remote="24849972320" /><file name="4.png" server="69.36.11.79" local="3328821220" remote="24849972380" /><file name="5.png" server="69.36.11.79" local="3328821220" remote="24849972380" /><file name="6.png" server="69.36.11.79" local="3328821220" remote="24849972380" /><file name="7.png" server="69.36.11.79" local="3328821220" remote="24849972380" /><file name="8.png" server="69.36.11.79" local="3328821220" remote="24849972380" /><file name="9.png" server="69.36.11.79" local="3328821220" remote="24849972380" /></dwsync>